elucid/__init__.py
elucid/config.py
elucid/catalogs/__init__.py
elucid/catalogs/filter.py
elucid/catalogs/halo_catalog.py
elucid/domain/__init__.py
elucid/domain/cell.py
elucid/domain/domain_locator.py
elucid/domain/domain_profile.py
elucid/domain/domain_sampler.py
elucid/domain/domain_sampler_mpi.py
elucid/gen_util/__init__.py
elucid/gen_util/abc.py
elucid/gen_util/fft.py
elucid/gen_util/field.py
elucid/gen_util/mass_assignment.py
elucid/gen_util/mesh.py
elucid/gen_util/scheduler.py
elucid/gen_util/test_data.py
elucid/gen_util/fields/__init__.py
elucid/gen_util/fields/non_periodic.py
elucid/gen_util/fields/periodic.py
elucid/gen_util/fields/smoothers.py
elucid/geometry/__init__.py
elucid/geometry/frame.py
elucid/geometry/mask.py
elucid/pde/__init__.py
elucid/pde/field.py
elucid/pde/peculiar_velocity.py
elucid/pde/poisson.py
elucid/pde/theory.py
elucid/sims/__init__.py
elucid/sims/cell_storage.py
elucid/sims/density_field.py
elucid/sims/halo_profile.py
elucid/sims/particle_volume.py
elucid/sims/peano.py
elucid/sims/region_loader.py
elucid/sims/sim_info_for_elucid.py
elucid-0.0.1.dist-info/licenses/LICENSE
elucid-0.0.1.dist-info/METADATA
elucid-0.0.1.dist-info/WHEEL
elucid-0.0.1.dist-info/top_level.txt
elucid-0.0.1.dist-info/RECORD
